EMBL2checklists/CLIOps.py
EMBL2checklists/ChecklistOps.py
EMBL2checklists/EMBL2checklistsMain.py
EMBL2checklists/GUIOps.py
EMBL2checklists/PrerequisiteOps.py
EMBL2checklists/__init__.py
EMBL2checklists/globalVariables.py
EMBL2checklists-0.6.data/scripts/EMBL2checklists_launcher_CLI.py
EMBL2checklists-0.6.data/scripts/EMBL2checklists_launcher_GUI.py
EMBL2checklists-0.6.dist-info/METADATA
EMBL2checklists-0.6.dist-info/RECORD
EMBL2checklists-0.6.dist-info/WHEEL
EMBL2checklists-0.6.dist-info/entry_points.txt
EMBL2checklists-0.6.dist-info/top_level.txt
