Metadata-Version: 2.1
Name: EMBL2checklists
Version: 0.6
Summary: Converts EMBL- or GenBank-formatted flatfiles to submission checklists (i.e., tab-separated spreadsheets) for submission to ENA via the interactive Webin submission system
Home-page: https://github.com/michaelgruenstaeudl/EMBL2checklists
Author: Michael Gruenstaeudl, PhD
Author-email: m.gruenstaeudl@fu-berlin.de
License: BSD
Keywords: novel DNA sequences,public sequence databases,European Nucleotide Archive,file conversion,data upload
Platform: UNKNOWN
Classifier: Development Status :: 4 - Beta
Classifier: License :: OSI Approved :: BSD License
Classifier: Programming Language :: Python :: 2.7
Classifier: Intended Audience :: Science/Research
Classifier: Topic :: Scientific/Engineering :: Bio-Informatics
Requires-Dist: biopython
Requires-Dist: argparse
